telnetlib/__init__.py
telnetlib_313_and_up-3.13.1.dist-info/License.txt
telnetlib_313_and_up-3.13.1.dist-info/WHEEL
telnetlib_313_and_up-3.13.1.dist-info/METADATA
telnetlib_313_and_up-3.13.1.dist-info/RECORD
