Metadata-Version: 2.1
Name: telnetlib-313-and-up
Version: 3.13.1
Summary: copy of telnetlib for python 3.13+
Keywords: telnet
Author: Guido van Rossum
Author-email: guido@python.org
Requires-Python: >=3.13
Classifier: Programming Language :: Python :: 3
